svd_training/__init__.py
svd_training/model_keys.py
svd_training/svd_linear.py
svd_training/svd_llama3_model.py
svd_training/svd_mistral-v0.1_model.py
svd_training/svd_mistralv01_model.py
svd_training/svd_model.py
svd_training/svd_phi3-mini_model.py
svd_training/svd_phi3mini_model.py
svd_training/variables.py
svd_training-0.0.2.dist-info/METADATA
svd_training-0.0.2.dist-info/WHEEL
svd_training-0.0.2.dist-info/top_level.txt
svd_training-0.0.2.dist-info/RECORD
