Metadata-Version: 2.1
Name: svd-training
Version: 0.0.2
Summary: A training helper for LLM.
Home-page: http://github.com/fractalego/svd-training
Author: Alberto Cetoli
Author-email: alberto@fractalego.io
Classifier: License :: OSI Approved :: MIT License
Requires-Dist: transformers (==4.41.0)
Requires-Dist: torch (==2.3.0)
